LICENSE.txt
README.md
setup.py
ish_parser/CloudCoverage.py
ish_parser/Constant.py
ish_parser/Direction.py
ish_parser/Distance.py
ish_parser/Humidity.py
ish_parser/Irradiance.py
ish_parser/Minutes.py
ish_parser/Observation.py
ish_parser/Pressure.py
ish_parser/ReportType.py
ish_parser/Speed.py
ish_parser/Temperature.py
ish_parser/Units.py
ish_parser/__init__.py
ish_parser/ish_parser.py
ish_parser/ish_report.py
ish_parser.egg-info/PKG-INFO
ish_parser.egg-info/SOURCES.txt
ish_parser.egg-info/dependency_links.txt
ish_parser.egg-info/top_level.txt
ish_parser/Components/BaseComponent.py
ish_parser/Components/PrecipitationComponent.py
ish_parser/Components/PresentWeatherComponent.py
ish_parser/Components/PresentWeatherConditionComponent.py
ish_parser/Components/PressureComponent.py
ish_parser/Components/SkyConditionObservationComponent.py
ish_parser/Components/SkyCoverComponent.py
ish_parser/Components/SkyCoverSummationComponent.py
ish_parser/Components/SnowDepthComponent.py
ish_parser/Components/SolarIrradianceComponent.py
ish_parser/Components/WindObservationComponent.py
ish_parser/Components/__init__.py