Metadata-Version: 2.1
Name: ish-parser
Version: 0.0.25
Summary: Parser for NOAA ISH (integrated surface hourly) reports
Home-page: https://github.com/haydenth/ish_parser
Author: thayden
Author-email: thayden@gmail.com
License: UNKNOWN
Platform: UNKNOWN
License-File: LICENSE.txt
